sotools/__init__.py
sotools/ldd.py
sotools/libraryset.py
sotools/linker.py
sotools/util.py
sotools/version.py
sotools/dl_cache/__init__.py
sotools/dl_cache/dl_cache.py
sotools/dl_cache/flags.py
sotools/dl_cache/structure.py
sotools/dl_cache/extensions/__init__.py
sotools/dl_cache/extensions/generator.py
sotools/dl_cache/extensions/hwcaps.py
sotools/scripts/__init__.py
sotools/scripts/ldconfig.py
sotools/scripts/ldd.py
sotools/scripts/sowhich.py
python_sotools-0.1.3.dist-info/METADATA
python_sotools-0.1.3.dist-info/WHEEL
python_sotools-0.1.3.dist-info/entry_points.txt
python_sotools-0.1.3.dist-info/top_level.txt
python_sotools-0.1.3.dist-info/RECORD
