Metadata-Version: 2.1
Name: python-sotools
Version: 0.1.3
Summary: Collection of dynamic linking tools
Author-email: Jean-Baptiste Skutnik <jb.skutnik@gmail.com>
License: BSD-3-Clause
Keywords: elf,linking,linux,libraries,system
Classifier: Intended Audience :: Developers
Classifier: Environment :: Console
Classifier: Operating System :: POSIX :: Linux
Classifier: Programming Language :: Python
Classifier: Programming Language :: Python :: 3
Requires-Python: >=3.7
Requires-Dist: pyelftools
